{
  "exportedAt": "2026-03-29T18:49:50.315637+00:00",
  "count": 116,
  "prices": [
    {
      "fuelType": "diesel",
      "reportCount": 2,
      "updatedAt": "2026-03-26T17:34:18.585506",
      "price": 24.09,
      "stationId": "osm_1118788394"
    },
    {
      "fuelType": "petrol95",
      "reportCount": 2,
      "updatedAt": "2026-03-26T17:34:17.786558",
      "price": 21.08,
      "stationId": "osm_1118788394"
    },
    {
      "fuelType": "diesel",
      "reportCount": 1,
      "stationId": "osm_1288290960",
      "price": 24.99,
      "updatedAt": "2026-03-25T20:37:00.776206"
    },
    {
      "fuelType": "petrol95",
      "reportCount": 1,
      "stationId": "osm_1288290960",
      "price": 22.49,
      "updatedAt": "2026-03-25T20:37:00.254294"
    },
    {
      "fuelType": "petrol98",
      "reportCount": 1,
      "stationId": "osm_1288290960",
      "price": 24.56,
      "updatedAt": "2026-03-25T20:42:38.012874"
    },
    {
      "fuelType": "diesel",
      "reportCount": 4,
      "stationId": "osm_177201618",
      "price": 26.45,
      "updatedAt": "2026-03-22T13:03:58.775687"
    },
    {
      "fuelType": "petrol95",
      "reportCount": 4,
      "updatedAt": "2026-03-22T13:03:57.815112",
      "price": 24.07,
      "stationId": "osm_177201618"
    },
    {
      "fuelType": "diesel",
      "reportCount": 1,
      "stationId": "osm_1857873544",
      "price": 29.29,
      "updatedAt": "2026-03-24T21:12:54.619682"
    },
    {
      "fuelType": "petrol95",
      "reportCount": 1,
      "stationId": "osm_1857873544",
      "price": 26.09,
      "updatedAt": "2026-03-24T21:12:54.027684"
    },
    {
      "fuelType": "diesel",
      "reportCount": 1,
      "stationId": "osm_1857873548",
      "price": 29.29,
      "updatedAt": "2026-03-24T21:12:26.397409"
    },
    {
      "fuelType": "petrol95",
      "reportCount": 1,
      "stationId": "osm_1857873548",
      "price": 26.09,
      "updatedAt": "2026-03-24T21:12:25.783026"
    },
    {
      "fuelType": "diesel",
      "reportCount": 1,
      "stationId": "osm_1898575788",
      "price": 26.39,
      "updatedAt": "2026-03-26T17:44:50.385667"
    },
    {
      "fuelType": "petrol95",
      "reportCount": 1,
      "updatedAt": "2026-03-26T17:44:49.755508",
      "price": 24.29,
      "stationId": "osm_1898575788"
    },
    {
      "fuelType": "diesel",
      "reportCount": 1,
      "stationId": "osm_1942735125",
      "price": 28.04,
      "updatedAt": "2026-03-28T12:23:56.716389"
    },
    {
      "fuelType": "petrol95",
      "reportCount": 1,
      "updatedAt": "2026-03-28T12:23:55.991674",
      "price": 25.41,
      "stationId": "osm_1942735125"
    },
    {
      "fuelType": "diesel",
      "reportCount": 2,
      "updatedAt": "2026-03-29T13:18:08.856559",
      "price": 27.59,
      "stationId": "osm_269783601"
    },
    {
      "fuelType": "petrol95",
      "reportCount": 2,
      "updatedAt": "2026-03-29T13:18:08.133123",
      "price": 24.85,
      "stationId": "osm_269783601"
    },
    {
      "fuelType": "diesel",
      "reportCount": 2,
      "stationId": "osm_269783602",
      "price": 27.39,
      "updatedAt": "2026-03-29T13:14:51.885429"
    },
    {
      "fuelType": "petrol95",
      "reportCount": 2,
      "stationId": "osm_269783602",
      "price": 24.65,
      "updatedAt": "2026-03-29T13:14:51.198373"
    },
    {
      "fuelType": "diesel",
      "reportCount": 2,
      "stationId": "osm_29569937",
      "price": 25.59,
      "updatedAt": "2026-03-27T11:55:54.093385"
    },
    {
      "fuelType": "petrol95",
      "reportCount": 2,
      "stationId": "osm_29569937",
      "price": 21.99,
      "updatedAt": "2026-03-27T11:55:53.123487"
    },
    {
      "fuelType": "diesel",
      "reportCount": 3,
      "updatedAt": "2026-03-28T16:29:21.594439",
      "price": 27.97,
      "stationId": "osm_29762195"
    },
    {
      "fuelType": "petrol95",
      "reportCount": 3,
      "stationId": "osm_29762195",
      "price": 25.2,
      "updatedAt": "2026-03-28T16:29:20.646766"
    },
    {
      "fuelType": "diesel",
      "reportCount": 2,
      "updatedAt": "2026-03-27T12:04:13.697512",
      "price": 25.59,
      "stationId": "osm_30124952"
    },
    {
      "fuelType": "petrol95",
      "reportCount": 2,
      "updatedAt": "2026-03-27T12:04:12.427681",
      "price": 21.99,
      "stationId": "osm_30124952"
    },
    {
      "fuelType": "diesel",
      "reportCount": 1,
      "updatedAt": "2026-03-27T12:13:57.021005",
      "price": 25.79,
      "stationId": "osm_30767154"
    },
    {
      "fuelType": "petrol95",
      "reportCount": 1,
      "stationId": "osm_30767154",
      "price": 22.41,
      "updatedAt": "2026-03-27T12:13:55.944591"
    },
    {
      "fuelType": "diesel",
      "reportCount": 1,
      "stationId": "osm_3289060460",
      "price": 26.49,
      "updatedAt": "2026-03-26T17:45:25.271043"
    },
    {
      "fuelType": "petrol95",
      "reportCount": 1,
      "updatedAt": "2026-03-26T17:45:24.453607",
      "price": 24.39,
      "stationId": "osm_3289060460"
    },
    {
      "fuelType": "diesel",
      "reportCount": 1,
      "stationId": "osm_35784040",
      "price": 25.59,
      "updatedAt": "2026-03-27T12:09:11.487061"
    },
    {
      "fuelType": "petrol95",
      "reportCount": 1,
      "stationId": "osm_35784040",
      "price": 22.19,
      "updatedAt": "2026-03-27T12:09:10.650998"
    },
    {
      "fuelType": "diesel",
      "reportCount": 11,
      "stationId": "osm_40655415",
      "price": 26.19,
      "updatedAt": "2026-03-26T21:06:51.659869"
    },
    {
      "fuelType": "petrol95",
      "reportCount": 12,
      "stationId": "osm_40655415",
      "price": 23.19,
      "updatedAt": "2026-03-26T21:06:50.304138"
    },
    {
      "fuelType": "diesel",
      "reportCount": 1,
      "updatedAt": "2026-03-27T01:12:56.934180",
      "price": 25.19,
      "stationId": "osm_494037707"
    },
    {
      "fuelType": "petrol95",
      "reportCount": 1,
      "stationId": "osm_494037707",
      "price": 22.69,
      "updatedAt": "2026-03-27T01:12:56.341259"
    },
    {
      "fuelType": "diesel",
      "reportCount": 1,
      "stationId": "osm_534910052",
      "price": 25.19,
      "updatedAt": "2026-03-27T01:14:56.355985"
    },
    {
      "fuelType": "petrol95",
      "reportCount": 1,
      "stationId": "osm_534910052",
      "price": 22.39,
      "updatedAt": "2026-03-27T01:14:55.697733"
    },
    {
      "fuelType": "diesel",
      "reportCount": 2,
      "stationId": "osm_6066333688",
      "price": 27.37,
      "updatedAt": "2026-03-25T07:00:45.666782"
    },
    {
      "fuelType": "petrol95",
      "reportCount": 2,
      "stationId": "osm_6066333688",
      "price": 25.04,
      "updatedAt": "2026-03-25T07:00:44.798565"
    },
    {
      "fuelType": "diesel",
      "reportCount": 1,
      "updatedAt": "2026-03-22T22:21:03.860930",
      "price": 26.99,
      "stationId": "osm_6066895913"
    },
    {
      "fuelType": "diesel",
      "reportCount": 1,
      "stationId": "osm_6066895917",
      "price": 24.79,
      "updatedAt": "2026-03-25T20:46:01.184812"
    },
    {
      "fuelType": "petrol95",
      "reportCount": 1,
      "updatedAt": "2026-03-25T20:46:00.444811",
      "price": 22.29,
      "stationId": "osm_6066895917"
    },
    {
      "fuelType": "diesel",
      "reportCount": 1,
      "stationId": "osm_6082905353",
      "price": 26.39,
      "updatedAt": "2026-03-23T07:04:45.235860"
    },
    {
      "fuelType": "petrol95",
      "reportCount": 1,
      "stationId": "osm_6082905353",
      "price": 25.39,
      "updatedAt": "2026-03-23T07:04:44.647420"
    },
    {
      "fuelType": "diesel",
      "reportCount": 1,
      "stationId": "osm_6083131336",
      "price": 25.19,
      "updatedAt": "2026-03-23T16:36:31.099047"
    },
    {
      "fuelType": "petrol95",
      "reportCount": 1,
      "stationId": "osm_6083131336",
      "price": 22.19,
      "updatedAt": "2026-03-23T16:36:30.291620"
    },
    {
      "fuelType": "diesel",
      "reportCount": 1,
      "updatedAt": "2026-03-27T03:16:05.715154",
      "price": 25.79,
      "stationId": "osm_6083131342"
    },
    {
      "fuelType": "petrol95",
      "reportCount": 1,
      "stationId": "osm_6083131342",
      "price": 22.19,
      "updatedAt": "2026-03-27T03:16:05.014796"
    },
    {
      "fuelType": "diesel",
      "reportCount": 3,
      "updatedAt": "2026-03-22T13:04:46.913007",
      "price": 26.45,
      "stationId": "osm_6093787872"
    },
    {
      "fuelType": "petrol95",
      "reportCount": 3,
      "updatedAt": "2026-03-22T13:04:45.604981",
      "price": 24.07,
      "stationId": "osm_6093787872"
    },
    {
      "fuelType": "petrol98",
      "reportCount": 2,
      "updatedAt": "2026-03-22T13:04:46.356747",
      "price": 26.57,
      "stationId": "osm_6093787872"
    },
    {
      "fuelType": "diesel",
      "reportCount": 15,
      "updatedAt": "2026-03-26T21:06:32.591082",
      "price": 27.15,
      "stationId": "osm_6093788692"
    },
    {
      "fuelType": "petrol95",
      "reportCount": 17,
      "updatedAt": "2026-03-26T21:06:30.853772",
      "price": 24.55,
      "stationId": "osm_6093788692"
    },
    {
      "fuelType": "petrol98",
      "reportCount": 8,
      "stationId": "osm_6093788692",
      "price": 26.35,
      "updatedAt": "2026-03-26T21:06:31.783536"
    },
    {
      "fuelType": "diesel",
      "reportCount": 2,
      "stationId": "osm_6093873057",
      "price": 25.39,
      "updatedAt": "2026-03-27T11:59:45.267227"
    },
    {
      "fuelType": "petrol95",
      "reportCount": 2,
      "updatedAt": "2026-03-27T11:59:44.397427",
      "price": 21.99,
      "stationId": "osm_6093873057"
    },
    {
      "fuelType": "diesel",
      "reportCount": 1,
      "updatedAt": "2026-03-26T17:12:39.126120",
      "price": 24.19,
      "stationId": "osm_6094004702"
    },
    {
      "fuelType": "petrol95",
      "reportCount": 1,
      "updatedAt": "2026-03-26T17:12:38.430213",
      "price": 22.18,
      "stationId": "osm_6094004702"
    },
    {
      "fuelType": "diesel",
      "reportCount": 9,
      "updatedAt": "2026-03-25T15:49:20.605219",
      "price": 27.36,
      "stationId": "osm_6117259980"
    },
    {
      "fuelType": "petrol95",
      "reportCount": 9,
      "stationId": "osm_6117259980",
      "price": 24.66,
      "updatedAt": "2026-03-25T15:49:19.907930"
    },
    {
      "fuelType": "diesel",
      "reportCount": 2,
      "updatedAt": "2026-03-29T13:21:53.172633",
      "price": 27.39,
      "stationId": "osm_6117259981"
    },
    {
      "fuelType": "petrol95",
      "reportCount": 2,
      "stationId": "osm_6117259981",
      "price": 24.65,
      "updatedAt": "2026-03-29T13:21:52.475899"
    },
    {
      "fuelType": "diesel",
      "reportCount": 1,
      "updatedAt": "2026-03-25T20:41:19.498929",
      "price": 24.79,
      "stationId": "osm_6119347976"
    },
    {
      "fuelType": "petrol95",
      "reportCount": 1,
      "updatedAt": "2026-03-25T20:41:18.829038",
      "price": 22.29,
      "stationId": "osm_6119347976"
    },
    {
      "fuelType": "diesel",
      "reportCount": 4,
      "updatedAt": "2026-03-28T23:04:50.998233",
      "price": 25.27,
      "stationId": "osm_6119891066"
    },
    {
      "fuelType": "petrol95",
      "reportCount": 4,
      "updatedAt": "2026-03-28T23:04:50.123526",
      "price": 21.77,
      "stationId": "osm_6119891066"
    },
    {
      "fuelType": "diesel",
      "reportCount": 1,
      "updatedAt": "2026-03-25T20:37:29.720404",
      "price": 24.79,
      "stationId": "osm_765936629"
    },
    {
      "fuelType": "petrol95",
      "reportCount": 1,
      "updatedAt": "2026-03-25T20:37:29.181045",
      "price": 22.29,
      "stationId": "osm_765936629"
    },
    {
      "fuelType": "diesel",
      "reportCount": 1,
      "stationId": "osm_849975805",
      "price": 24.99,
      "updatedAt": "2026-03-27T01:54:02.521183"
    },
    {
      "fuelType": "petrol95",
      "reportCount": 1,
      "updatedAt": "2026-03-27T01:54:01.840746",
      "price": 22.19,
      "stationId": "osm_849975805"
    },
    {
      "fuelType": "diesel",
      "reportCount": 1,
      "updatedAt": "2026-03-26T21:17:56.447117",
      "price": 25.99,
      "stationId": "osm_849976088"
    },
    {
      "fuelType": "petrol95",
      "reportCount": 1,
      "stationId": "osm_849976088",
      "price": 23.99,
      "updatedAt": "2026-03-26T21:17:55.623013"
    },
    {
      "fuelType": "diesel",
      "reportCount": 10,
      "stationId": "osm_8791397001",
      "price": 26.11,
      "updatedAt": "2026-03-26T21:07:13.587221"
    },
    {
      "fuelType": "petrol95",
      "reportCount": 10,
      "stationId": "osm_8791397001",
      "price": 23.11,
      "updatedAt": "2026-03-26T21:07:11.919005"
    },
    {
      "fuelType": "diesel",
      "reportCount": 1,
      "updatedAt": "2026-03-25T20:36:21.070712",
      "price": 24.99,
      "stationId": "user_YQmG7kBoVi7W5tQk6Qq2"
    },
    {
      "fuelType": "petrol95",
      "reportCount": 1,
      "updatedAt": "2026-03-25T20:36:20.383013",
      "price": 22.49,
      "stationId": "user_YQmG7kBoVi7W5tQk6Qq2"
    },
    {
      "fuelType": "diesel",
      "reportCount": 1,
      "stationId": "user_t9IP5iR7UH7S82E6ukTU",
      "price": 26.49,
      "updatedAt": "2026-03-26T18:44:00.964989"
    },
    {
      "fuelType": "petrol95",
      "reportCount": 1,
      "updatedAt": "2026-03-26T18:44:00.339201",
      "price": 22.49,
      "stationId": "user_t9IP5iR7UH7S82E6ukTU"
    },
    {
      "fuelType": "diesel",
      "reportCount": 1,
      "updatedAt": "2026-03-25T20:24:43.896655",
      "price": 24.99,
      "stationId": "user_xAYrFcZb2UA2kUJHTrIv"
    },
    {
      "fuelType": "petrol95",
      "reportCount": 1,
      "updatedAt": "2026-03-25T20:24:43.194502",
      "price": 21.99,
      "stationId": "user_xAYrFcZb2UA2kUJHTrIv"
    },
    {
      "fuelType": "petrol95",
      "reportCount": 1,
      "stationId": "osm_599888142",
      "price": 21.77,
      "updatedAt": "2026-03-28T15:27:33.499869"
    },
    {
      "fuelType": "diesel",
      "reportCount": 1,
      "stationId": "osm_599888142",
      "price": 25.27,
      "updatedAt": "2026-03-28T15:27:34.271898"
    },
    {
      "fuelType": "petrol95",
      "reportCount": 1,
      "updatedAt": "2026-03-28T19:20:37.536337",
      "price": 26.05,
      "stationId": "osm_6120028099"
    },
    {
      "fuelType": "diesel",
      "reportCount": 1,
      "stationId": "osm_6120028099",
      "price": 29.2,
      "updatedAt": "2026-03-28T19:20:38.296031"
    },
    {
      "fuelType": "petrol95",
      "reportCount": 1,
      "updatedAt": "2026-03-28T20:17:20.120099",
      "price": 21.59,
      "stationId": "osm_12816193600"
    },
    {
      "fuelType": "diesel",
      "reportCount": 1,
      "updatedAt": "2026-03-28T20:17:20.918664",
      "price": 24.99,
      "stationId": "osm_12816193600"
    },
    {
      "fuelType": "petrol95",
      "reportCount": 1,
      "stationId": "osm_6067032055",
      "price": 21.79,
      "updatedAt": "2026-03-28T20:17:36.545783"
    },
    {
      "fuelType": "diesel",
      "reportCount": 1,
      "updatedAt": "2026-03-28T20:17:37.211548",
      "price": 25.19,
      "stationId": "osm_6067032055"
    },
    {
      "fuelType": "petrol95",
      "reportCount": 1,
      "stationId": "osm_827364296",
      "price": 21.49,
      "updatedAt": "2026-03-28T20:41:54.407296"
    },
    {
      "fuelType": "diesel",
      "reportCount": 1,
      "updatedAt": "2026-03-28T20:41:55.205817",
      "price": 25.49,
      "stationId": "osm_827364296"
    },
    {
      "fuelType": "petrol95",
      "reportCount": 1,
      "updatedAt": "2026-03-28T20:59:26.176009",
      "price": 21.99,
      "stationId": "osm_6066248800"
    },
    {
      "fuelType": "diesel",
      "reportCount": 1,
      "updatedAt": "2026-03-28T20:59:26.924200",
      "price": 25.49,
      "stationId": "osm_6066248800"
    },
    {
      "fuelType": "petrol95",
      "reportCount": 1,
      "updatedAt": "2026-03-28T21:01:11.031262",
      "price": 21.79,
      "stationId": "osm_6093918078"
    },
    {
      "fuelType": "diesel",
      "reportCount": 1,
      "updatedAt": "2026-03-28T21:01:11.856979",
      "price": 25.29,
      "stationId": "osm_6093918078"
    },
    {
      "fuelType": "petrol95",
      "reportCount": 1,
      "updatedAt": "2026-03-28T21:03:18.548136",
      "price": 21.99,
      "stationId": "osm_6093918250"
    },
    {
      "fuelType": "diesel",
      "reportCount": 1,
      "stationId": "osm_6093918250",
      "price": 25.49,
      "updatedAt": "2026-03-28T21:03:19.385829"
    },
    {
      "fuelType": "petrol95",
      "reportCount": 1,
      "updatedAt": "2026-03-28T21:04:55.485598",
      "price": 21.79,
      "stationId": "osm_443370472"
    },
    {
      "fuelType": "diesel",
      "reportCount": 1,
      "updatedAt": "2026-03-28T21:04:56.235553",
      "price": 25.29,
      "stationId": "osm_443370472"
    },
    {
      "fuelType": "petrol95",
      "reportCount": 1,
      "stationId": "osm_5384664821",
      "price": 21.79,
      "updatedAt": "2026-03-28T21:05:23.240123"
    },
    {
      "fuelType": "diesel",
      "reportCount": 1,
      "updatedAt": "2026-03-28T21:05:23.852129",
      "price": 25.29,
      "stationId": "osm_5384664821"
    },
    {
      "fuelType": "petrol95",
      "reportCount": 1,
      "updatedAt": "2026-03-28T21:05:40.756516",
      "price": 21.99,
      "stationId": "osm_442149044"
    },
    {
      "fuelType": "diesel",
      "reportCount": 1,
      "stationId": "osm_442149044",
      "price": 25.49,
      "updatedAt": "2026-03-28T21:05:42.650709"
    },
    {
      "fuelType": "petrol95",
      "reportCount": 1,
      "updatedAt": "2026-03-28T21:09:11.768022",
      "price": 21.79,
      "stationId": "osm_1016676523"
    },
    {
      "fuelType": "diesel",
      "reportCount": 1,
      "stationId": "osm_1016676523",
      "price": 25.29,
      "updatedAt": "2026-03-28T21:09:12.889626"
    },
    {
      "fuelType": "petrol95",
      "reportCount": 1,
      "updatedAt": "2026-03-28T21:12:26.136838",
      "price": 20.99,
      "stationId": "osm_686544454"
    },
    {
      "fuelType": "diesel",
      "reportCount": 1,
      "stationId": "osm_686544454",
      "price": 24.99,
      "updatedAt": "2026-03-28T21:12:26.904108"
    },
    {
      "fuelType": "petrol95",
      "reportCount": 1,
      "updatedAt": "2026-03-28T21:13:40.026841",
      "price": 25.29,
      "stationId": "osm_849975480"
    },
    {
      "fuelType": "diesel",
      "reportCount": 1,
      "updatedAt": "2026-03-28T21:13:40.787468",
      "price": 21.5,
      "stationId": "osm_849975480"
    },
    {
      "fuelType": "petrol95",
      "reportCount": 1,
      "stationId": "osm_6083131333",
      "price": 21.19,
      "updatedAt": "2026-03-28T21:20:14.172737"
    },
    {
      "fuelType": "diesel",
      "reportCount": 1,
      "stationId": "osm_6083131333",
      "price": 25.19,
      "updatedAt": "2026-03-28T21:20:14.951522"
    },
    {
      "fuelType": "petrol95",
      "reportCount": 1,
      "stationId": "osm_269783600",
      "price": 25.14,
      "updatedAt": "2026-03-29T13:09:07.463003"
    },
    {
      "fuelType": "diesel",
      "reportCount": 1,
      "updatedAt": "2026-03-29T13:09:08.181005",
      "price": 27.79,
      "stationId": "osm_269783600"
    },
    {
      "fuelType": "petrol95",
      "reportCount": 1,
      "updatedAt": "2026-03-29T13:27:01.171370",
      "price": 24.64,
      "stationId": "osm_4023377699"
    },
    {
      "fuelType": "diesel",
      "reportCount": 1,
      "stationId": "osm_4023377699",
      "price": 27.38,
      "updatedAt": "2026-03-29T13:27:01.857738"
    },
    {
      "fuelType": "petrol95",
      "reportCount": 1,
      "updatedAt": "2026-03-29T15:17:40.383205",
      "price": 21.85,
      "stationId": "osm_6119891063"
    },
    {
      "fuelType": "diesel",
      "reportCount": 1,
      "stationId": "osm_6119891063",
      "price": 24.88,
      "updatedAt": "2026-03-29T15:17:41.107791"
    }
  ]
}