{
  "exportedAt": "2026-03-22T10:47:50.666159+00:00",
  "count": 16,
  "prices": [
    {
      "price": 26.45,
      "stationId": "osm_177201618",
      "fuelType": "diesel",
      "updatedAt": "2026-03-21T22:11:39.938927",
      "reportCount": 3
    },
    {
      "price": 24.07,
      "stationId": "osm_177201618",
      "fuelType": "petrol95",
      "updatedAt": "2026-03-21T22:11:39.076511",
      "reportCount": 3
    },
    {
      "price": 26.44,
      "stationId": "osm_40655415",
      "fuelType": "diesel",
      "updatedAt": "2026-03-21T19:12:22.819121",
      "reportCount": 5
    },
    {
      "price": 24.06,
      "stationId": "osm_40655415",
      "fuelType": "petrol95",
      "updatedAt": "2026-03-21T19:12:22.220612",
      "reportCount": 6
    },
    {
      "price": 26.45,
      "stationId": "osm_6093787872",
      "fuelType": "diesel",
      "updatedAt": "2026-03-21T22:12:00.325512",
      "reportCount": 2
    },
    {
      "price": 24.07,
      "stationId": "osm_6093787872",
      "fuelType": "petrol95",
      "updatedAt": "2026-03-21T22:11:59.201934",
      "reportCount": 2
    },
    {
      "price": 26.57,
      "stationId": "osm_6093787872",
      "fuelType": "petrol98",
      "updatedAt": "2026-03-21T22:11:59.775809",
      "reportCount": 1
    },
    {
      "price": 26.44,
      "stationId": "osm_6093788692",
      "fuelType": "diesel",
      "updatedAt": "2026-03-21T22:10:22.738417",
      "reportCount": 10
    },
    {
      "price": 24.06,
      "stationId": "osm_6093788692",
      "fuelType": "petrol95",
      "updatedAt": "2026-03-21T22:10:21.865775",
      "reportCount": 12
    },
    {
      "price": 24.49,
      "stationId": "osm_6093788692",
      "fuelType": "petrol98",
      "updatedAt": "2026-03-21T20:16:42.783473",
      "reportCount": 4
    },
    {
      "price": 26.79,
      "stationId": "osm_6117259980",
      "fuelType": "diesel",
      "updatedAt": "2026-03-17T08:36:39.534041",
      "reportCount": 5
    },
    {
      "price": 25.29,
      "stationId": "osm_6117259980",
      "fuelType": "petrol95",
      "updatedAt": "2026-03-17T08:36:38.729753",
      "reportCount": 5
    },
    {
      "price": 25.12,
      "stationId": "osm_6117259981",
      "fuelType": "diesel",
      "updatedAt": "2026-03-07T11:22:50.297562",
      "reportCount": 1
    },
    {
      "price": 23.72,
      "stationId": "osm_6117259981",
      "fuelType": "petrol95",
      "updatedAt": "2026-03-07T11:22:49.804065",
      "reportCount": 1
    },
    {
      "price": 26.24,
      "stationId": "osm_8791397001",
      "fuelType": "diesel",
      "updatedAt": "2026-03-21T19:11:55.786636",
      "reportCount": 5
    },
    {
      "price": 23.86,
      "stationId": "osm_8791397001",
      "fuelType": "petrol95",
      "updatedAt": "2026-03-21T19:11:55.141214",
      "reportCount": 5
    }
  ]
}